Blinky.v
module Blinky(
  input   clock,
  input   reset,
  output  io_led0
);
  reg  led; // @[Main.scala 9:20]
  reg [5:0] counterWrap_c_value; // @[Counter.scala 61:40]
  wire  counterWrap_wrap_wrap = counterWrap_c_value == 6'h31; // @[Counter.scala 73:24]
  wire [5:0] _counterWrap_wrap_value_T_1 = counterWrap_c_value + 6'h1; // @[Counter.scala 77:24]
  assign io_led0 = led; // @[Main.scala 14:11]
  always @(posedge clock) begin
    if (reset) begin // @[Main.scala 9:20]
      led <= 1'h0; // @[Main.scala 9:20]
    end else if (counterWrap_wrap_wrap) begin // @[Main.scala 11:21]
      led <= ~led; // @[Main.scala 12:9]
    end
    if (reset) begin // @[Counter.scala 61:40]
      counterWrap_c_value <= 6'h0; // @[Counter.scala 61:40]
    end else if (counterWrap_wrap_wrap) begin // @[Counter.scala 87:20]
      counterWrap_c_value <= 6'h0; // @[Counter.scala 87:28]
    end else begin
      counterWrap_c_value <= _counterWrap_wrap_value_T_1; // @[Counter.scala 77:15]
    end
  end
endmodule

tb_Blinky.v
`timescale 1ns/100ps

module tb_Blinky;

parameter SYSCLK_PERIOD = 10;

reg SYSCLK;
reg NSYSRESET;

wire O_led;

integer i ;

initial
begin
    SYSCLK = 1'b0;
    NSYSRESET = 1'b1;
	
	#30;
	NSYSRESET = 1'b0;
end

/*iverilog */
initial
begin            
    $dumpfile("tb_Blinky.vcd");        //生成的vcd文件名称
    $dumpvars(0, tb_Blinky);    //tb模块名称
end
/*iverilog */
	
	initial begin
		#0;
		for(i = 0; i < 4000;i = i + 1)begin
			SYSCLK = !SYSCLK;
			#5;
		end
	end

Blinky Blinky_ut0 (
    // Inputs
    .reset( NSYSRESET ),
    .clock( SYSCLK ),

    // Outputs
    .io_led0( O_led )
);

endmodule

tb_Blinky.vcd
$date
	Tue Mar 04 00:08:03 2025
$end
$version
	Icarus Verilog
$end
$timescale
	100ps
$end
$scope module tb_Blinky $end
$var wire 1 ! O_led $end
$var parameter 32 " SYSCLK_PERIOD $end
$var reg 1 # NSYSRESET $end
$var reg 1 $ SYSCLK $end
$var integer 32 % i [31:0] $end
$scope module Blinky_ut0 $end
$var wire 1 $ clock $end
$var wire 1 ! io_led0 $end
$var wire 1 # reset $end
$var wire 1 & counterWrap_wrap_wrap $end
$var wire 6 ' _counterWrap_wrap_value_T_1 [5:0] $end
$var reg 6 ( counterWrap_c_value [5:0] $end
$var reg 1 ) led $end
$upscope $end
$upscope $end
$enddefinitions $end
$comment Show the parameter values. $end
$dumpall
b1010 "
$end
#0
$dumpvars
0)
b0 (
b1 '
0&
b0 %
1$
1#
0!
$end
#50
0$
b1 %
#100
1$
b10 %
#150
0$
b11 %
#200
1$
b100 %
#250
0$
b101 %
#300
b10 '
b1 (
1$
b110 %
0#
#350
0$
b111 %
#400
b11 '
b10 (
1$
b1000 %
#450
0$
b1001 %
#500
b100 '
b11 (
1$
b1010 %
#550
0$
b1011 %
#600
b101 '
b100 (
1$
b1100 %
#650
0$
b1101 %
#700
b110 '
b101 (
1$
b1110 %
#750
0$
b1111 %
#800
b111 '
b110 (
1$
b10000 %
#850
0$
b10001 %
#900
b1000 '
b111 (
1$
b10010 %
#950
0$
b10011 %
#1000
b1001 '
b1000 (
1$
b10100 %
#1050
0$
b10101 %
#1100
b1010 '
b1001 (
1$
b10110 %
#1150
0$
b10111 %
#1200
b1011 '
b1010 (
1$
b11000 %
#1250
0$
b11001 %
#1300
b1100 '
b1011 (
1$
b11010 %
#1350
0$
b11011 %
#1400
b1101 '
b1100 (
1$
b11100 %
#1450
0$
b11101 %
#1500
b1110 '
b1101 (
1$
b11110 %
#1550
0$
b11111 %
#1600
b1111 '
b1110 (
1$
b100000 %
#1650
0$
b100001 %
#1700
b10000 '
b1111 (
1$
b100010 %
#1750
0$
b100011 %
#1800
b10001 '
b10000 (
1$
b100100 %
#1850
0$
b100101 %
#1900
b10010 '
b10001 (
1$
b100110 %
#1950
0$
b100111 %
#2000
b10011 '
b10010 (
1$
b101000 %
#2050
0$
b101001 %
#2100
b10100 '
b10011 (
1$
b101010 %
#2150
0$
b101011 %
#2200
b10101 '
b10100 (
1$
b101100 %
#2250
0$
b101101 %
#2300
b10110 '
b10101 (
1$
b101110 %
#2350
0$
b101111 %
#2400
b10111 '
b10110 (
1$
b110000 %
#2450
0$
b110001 %
#2500
b11000 '
b10111 (
1$
b110010 %
#2550
0$
b110011 %
#2600
b11001 '
b11000 (
1$
b110100 %
#2650
0$
b110101 %
#2700
b11010 '
b11001 (
1$
b110110 %
#2750
0$
b110111 %
#2800
b11011 '
b11010 (
1$
b111000 %
#2850
0$
b111001 %
#2900
b11100 '
b11011 (
1$
b111010 %
#2950
0$
b111011 %
#3000
b11101 '
b11100 (
1$
b111100 %
#3050
0$
b111101 %
#3100
b11110 '
b11101 (
1$
b111110 %
#3150
0$
b111111 %
#3200
b11111 '
b11110 (
1$
b1000000 %
#3250
0$
b1000001 %
#3300
b100000 '
b11111 (
1$
b1000010 %
#3350
0$
b1000011 %
#3400
b100001 '
b100000 (
1$
b1000100 %
#3450
0$
b1000101 %
#3500
b100010 '
b100001 (
1$
b1000110 %
#3550
0$
b1000111 %
#3600
b100011 '
b100010 (
1$
b1001000 %
#3650
0$
b1001001 %
#3700
b100100 '
b100011 (
1$
b1001010 %
#3750
0$
b1001011 %
#3800
b100101 '
b100100 (
1$
b1001100 %
#3850
0$
b1001101 %
#3900
b100110 '
b100101 (
1$
b1001110 %
#3950
0$
b1001111 %
#4000
b100111 '
b100110 (
1$
b1010000 %
#4050
0$
b1010001 %
#4100
b101000 '
b100111 (
1$
b1010010 %
#4150
0$
b1010011 %
#4200
b101001 '
b101000 (
1$
b1010100 %
#4250
0$
b1010101 %
#4300
b101010 '
b101001 (
1$
b1010110 %
#4350
0$
b1010111 %
#4400
b101011 '
b101010 (
1$
b1011000 %
#4450
0$
b1011001 %
#4500
b101100 '
b101011 (
1$
b1011010 %
#4550
0$
b1011011 %
#4600
b101101 '
b101100 (
1$
b1011100 %
#4650
0$
b1011101 %
#4700
b101110 '
b101101 (
1$
b1011110 %
#4750
0$
b1011111 %
#4800
b101111 '
b101110 (
1$
b1100000 %
#4850
0$
b1100001 %
#4900
b110000 '
b101111 (
1$
b1100010 %
#4950
0$
b1100011 %
#5000
b110001 '
b110000 (
1$
b1100100 %
#5050
0$
b1100101 %
#5100
1&
b110010 '
b110001 (
1$
b1100110 %
#5150
0$
b1100111 %
#5200
0&
b1 '
b0 (
1!
1)
1$
b1101000 %
#5250
0$
b1101001 %
#5300
b10 '
b1 (
1$
b1101010 %
#5350
0$
b1101011 %
#5400
b11 '
b10 (
1$
b1101100 %
#5450
0$
b1101101 %
#5500
b100 '
b11 (
1$
b1101110 %
#5550
0$
b1101111 %
#5600
b101 '
b100 (
1$
b1110000 %
#5650
0$
b1110001 %
#5700
b110 '
b101 (
1$
b1110010 %
#5750
0$
b1110011 %
#5800
b111 '
b110 (
1$
b1110100 %
#5850
0$
b1110101 %
#5900
b1000 '
b111 (
1$
b1110110 %
#5950
0$
b1110111 %
#6000
b1001 '
b1000 (
1$
b1111000 %
#6050
0$
b1111001 %
#6100
b1010 '
b1001 (
1$
b1111010 %
#6150
0$
b1111011 %
#6200
b1011 '
b1010 (
1$
b1111100 %
#6250
0$
b1111101 %
#6300
b1100 '
b1011 (
1$
b1111110 %
#6350
0$
b1111111 %
#6400
b1101 '
b1100 (
1$
b10000000 %
#6450
0$
b10000001 %
#6500
b1110 '
b1101 (
1$
b10000010 %
#6550
0$
b10000011 %
#6600
b1111 '
b1110 (
1$
b10000100 %
#6650
0$
b10000101 %
#6700
b10000 '
b1111 (
1$
b10000110 %
#6750
0$
b10000111 %
#6800
b10001 '
b10000 (
1$
b10001000 %
#6850
0$
b10001001 %
#6900
b10010 '
b10001 (
1$
b10001010 %
#6950
0$
b10001011 %
#7000
b10011 '
b10010 (
1$
b10001100 %
#7050
0$
b10001101 %
#7100
b10100 '
b10011 (
1$
b10001110 %
#7150
0$
b10001111 %
#7200
b10101 '
b10100 (
1$
b10010000 %
#7250
0$
b10010001 %
#7300
b10110 '
b10101 (
1$
b10010010 %
#7350
0$
b10010011 %
#7400
b10111 '
b10110 (
1$
b10010100 %
#7450
0$
b10010101 %
#7500
b11000 '
b10111 (
1$
b10010110 %
#7550
0$
b10010111 %
#7600
b11001 '
b11000 (
1$
b10011000 %
#7650
0$
b10011001 %
#7700
b11010 '
b11001 (
1$
b10011010 %
#7750
0$
b10011011 %
#7800
b11011 '
b11010 (
1$
b10011100 %
#7850
0$
b10011101 %
#7900
b11100 '
b11011 (
1$
b10011110 %
#7950
0$
b10011111 %
#8000
b11101 '
b11100 (
1$
b10100000 %
#8050
0$
b10100001 %
#8100
b11110 '
b11101 (
1$
b10100010 %
#8150
0$
b10100011 %
#8200
b11111 '
b11110 (
1$
b10100100 %
#8250
0$
b10100101 %
#8300
b100000 '
b11111 (
1$
b10100110 %
#8350
0$
b10100111 %
#8400
b100001 '
b100000 (
1$
b10101000 %
#8450
0$
b10101001 %
#8500
b100010 '
b100001 (
1$
b10101010 %
#8550
0$
b10101011 %
#8600
b100011 '
b100010 (
1$
b10101100 %
#8650
0$
b10101101 %
#8700
b100100 '
b100011 (
1$
b10101110 %
#8750
0$
b10101111 %
#8800
b100101 '
b100100 (
1$
b10110000 %
#8850
0$
b10110001 %
#8900
b100110 '
b100101 (
1$
b10110010 %
#8950
0$
b10110011 %
#9000
b100111 '
b100110 (
1$
b10110100 %
#9050
0$
b10110101 %
#9100
b101000 '
b100111 (
1$
b10110110 %
#9150
0$
b10110111 %
#9200
b101001 '
b101000 (
1$
b10111000 %
#9250
0$
b10111001 %
#9300
b101010 '
b101001 (
1$
b10111010 %
#9350
0$
b10111011 %
#9400
b101011 '
b101010 (
1$
b10111100 %
#9450
0$
b10111101 %
#9500
b101100 '
b101011 (
1$
b10111110 %
#9550
0$
b10111111 %
#9600
b101101 '
b101100 (
1$
b11000000 %
#9650
0$
b11000001 %
#9700
b101110 '
b101101 (
1$
b11000010 %
#9750
0$
b11000011 %
#9800
b101111 '
b101110 (
1$
b11000100 %
#9850
0$
b11000101 %
#9900
b110000 '
b101111 (
1$
b11000110 %
#9950
0$
b11000111 %
#10000
b110001 '
b110000 (
1$
b11001000 %
#10050
0$
b11001001 %
#10100
1&
b110010 '
b110001 (
1$
b11001010 %
#10150
0$
b11001011 %
#10200
0&
b1 '
b0 (
0!
0)
1$
b11001100 %
#10250
0$
b11001101 %
#10300
b10 '
b1 (
1$
b11001110 %
#10350
0$
b11001111 %
#10400
b11 '
b10 (
1$
b11010000 %
#10450
0$
b11010001 %
#10500
b100 '
b11 (
1$
b11010010 %
#10550
0$
b11010011 %
#10600
b101 '
b100 (
1$
b11010100 %
#10650
0$
b11010101 %
#10700
b110 '
b101 (
1$
b11010110 %
#10750
0$
b11010111 %
#10800
b111 '
b110 (
1$
b11011000 %
#10850
0$
b11011001 %
#10900
b1000 '
b111 (
1$
b11011010 %
#10950
0$
b11011011 %
#11000
b1001 '
b1000 (
1$
b11011100 %
#11050
0$
b11011101 %
#11100
b1010 '
b1001 (
1$
b11011110 %
#11150
0$
b11011111 %
#11200
b1011 '
b1010 (
1$
b11100000 %
#11250
0$
b11100001 %
#11300
b1100 '
b1011 (
1$
b11100010 %
#11350
0$
b11100011 %
#11400
b1101 '
b1100 (
1$
b11100100 %
#11450
0$
b11100101 %
#11500
b1110 '
b1101 (
1$
b11100110 %
#11550
0$
b11100111 %
#11600
b1111 '
b1110 (
1$
b11101000 %
#11650
0$
b11101001 %
#11700
b10000 '
b1111 (
1$
b11101010 %
#11750
0$
b11101011 %
#11800
b10001 '
b10000 (
1$
b11101100 %
#11850
0$
b11101101 %
#11900
b10010 '
b10001 (
1$
b11101110 %
#11950
0$
b11101111 %
#12000
b10011 '
b10010 (
1$
b11110000 %
#12050
0$
b11110001 %
#12100
b10100 '
b10011 (
1$
b11110010 %
#12150
0$
b11110011 %
#12200
b10101 '
b10100 (
1$
b11110100 %
#12250
0$
b11110101 %
#12300
b10110 '
b10101 (
1$
b11110110 %
#12350
0$
b11110111 %
#12400
b10111 '
b10110 (
1$
b11111000 %
#12450
0$
b11111001 %
#12500
b11000 '
b10111 (
1$
b11111010 %
#12550
0$
b11111011 %
#12600
b11001 '
b11000 (
1$
b11111100 %
#12650
0$
b11111101 %
#12700
b11010 '
b11001 (
1$
b11111110 %
#12750
0$
b11111111 %
#12800
b11011 '
b11010 (
1$
b100000000 %
#12850
0$
b100000001 %
#12900
b11100 '
b11011 (
1$
b100000010 %
#12950
0$
b100000011 %
#13000
b11101 '
b11100 (
1$
b100000100 %
#13050
0$
b100000101 %
#13100
b11110 '
b11101 (
1$
b100000110 %
#13150
0$
b100000111 %
#13200
b11111 '
b11110 (
1$
b100001000 %
#13250
0$
b100001001 %
#13300
b100000 '
b11111 (
1$
b100001010 %
#13350
0$
b100001011 %
#13400
b100001 '
b100000 (
1$
b100001100 %
#13450
0$
b100001101 %
#13500
b100010 '
b100001 (
1$
b100001110 %
#13550
0$
b100001111 %
#13600
b100011 '
b100010 (
1$
b100010000 %
#13650
0$
b100010001 %
#13700
b100100 '
b100011 (
1$
b100010010 %
#13750
0$
b100010011 %
#13800
b100101 '
b100100 (
1$
b100010100 %
#13850
0$
b100010101 %
#13900
b100110 '
b100101 (
1$
b100010110 %
#13950
0$
b100010111 %
#14000
b100111 '
b100110 (
1$
b100011000 %
#14050
0$
b100011001 %
#14100
b101000 '
b100111 (
1$
b100011010 %
#14150
0$
b100011011 %
#14200
b101001 '
b101000 (
1$
b100011100 %
#14250
0$
b100011101 %
#14300
b101010 '
b101001 (
1$
b100011110 %
#14350
0$
b100011111 %
#14400
b101011 '
b101010 (
1$
b100100000 %
#14450
0$
b100100001 %
#14500
b101100 '
b101011 (
1$
b100100010 %
#14550
0$
b100100011 %
#14600
b101101 '
b101100 (
1$
b100100100 %
#14650
0$
b100100101 %
#14700
b101110 '
b101101 (
1$
b100100110 %
#14750
0$
b100100111 %
#14800
b101111 '
b101110 (
1$
b100101000 %
#14850
0$
b100101001 %
#14900
b110000 '
b101111 (
1$
b100101010 %
#14950
0$
b100101011 %
#15000
b110001 '
b110000 (
1$
b100101100 %
#15050
0$
b100101101 %
#15100
1&
b110010 '
b110001 (
1$
b100101110 %
#15150
0$
b100101111 %
#15200
0&
b1 '
b0 (
1!
1)
1$
b100110000 %
#15250
0$
b100110001 %
#15300
b10 '
b1 (
1$
b100110010 %
#15350
0$
b100110011 %
#15400
b11 '
b10 (
1$
b100110100 %
#15450
0$
b100110101 %
#15500
b100 '
b11 (
1$
b100110110 %
#15550
0$
b100110111 %
#15600
b101 '
b100 (
1$
b100111000 %
#15650
0$
b100111001 %
#15700
b110 '
b101 (
1$
b100111010 %
#15750
0$
b100111011 %
#15800
b111 '
b110 (
1$
b100111100 %
#15850
0$
b100111101 %
#15900
b1000 '
b111 (
1$
b100111110 %
#15950
0$
b100111111 %
#16000
b1001 '
b1000 (
1$
b101000000 %
#16050
0$
b101000001 %
#16100
b1010 '
b1001 (
1$
b101000010 %
#16150
0$
b101000011 %
#16200
b1011 '
b1010 (
1$
b101000100 %
#16250
0$
b101000101 %
#16300
b1100 '
b1011 (
1$
b101000110 %
#16350
0$
b101000111 %
#16400
b1101 '
b1100 (
1$
b101001000 %
#16450
0$
b101001001 %
#16500
b1110 '
b1101 (
1$
b101001010 %
#16550
0$
b101001011 %
#16600
b1111 '
b1110 (
1$
b101001100 %
#16650
0$
b101001101 %
#16700
b10000 '
b1111 (
1$
b101001110 %
#16750
0$
b101001111 %
#16800
b10001 '
b10000 (
1$
b101010000 %
#16850
0$
b101010001 %
#16900
b10010 '
b10001 (
1$
b101010010 %
#16950
0$
b101010011 %
#17000
b10011 '
b10010 (
1$
b101010100 %
#17050
0$
b101010101 %
#17100
b10100 '
b10011 (
1$
b101010110 %
#17150
0$
b101010111 %
#17200
b10101 '
b10100 (
1$
b101011000 %
#17250
0$
b101011001 %
#17300
b10110 '
b10101 (
1$
b101011010 %
#17350
0$
b101011011 %
#17400
b10111 '
b10110 (
1$
b101011100 %
#17450
0$
b101011101 %
#17500
b11000 '
b10111 (
1$
b101011110 %
#17550
0$
b101011111 %
#17600
b11001 '
b11000 (
1$
b101100000 %
#17650
0$
b101100001 %
#17700
b11010 '
b11001 (
1$
b101100010 %
#17750
0$
b101100011 %
#17800
b11011 '
b11010 (
1$
b101100100 %
#17850
0$
b101100101 %
#17900
b11100 '
b11011 (
1$
b101100110 %
#17950
0$
b101100111 %
#18000
b11101 '
b11100 (
1$
b101101000 %
#18050
0$
b101101001 %
#18100
b11110 '
b11101 (
1$
b101101010 %
#18150
0$
b101101011 %
#18200
b11111 '
b11110 (
1$
b101101100 %
#18250
0$
b101101101 %
#18300
b100000 '
b11111 (
1$
b101101110 %
#18350
0$
b101101111 %
#18400
b100001 '
b100000 (
1$
b101110000 %
#18450
0$
b101110001 %
#18500
b100010 '
b100001 (
1$
b101110010 %
#18550
0$
b101110011 %
#18600
b100011 '
b100010 (
1$
b101110100 %
#18650
0$
b101110101 %
#18700
b100100 '
b100011 (
1$
b101110110 %
#18750
0$
b101110111 %
#18800
b100101 '
b100100 (
1$
b101111000 %
#18850
0$
b101111001 %
#18900
b100110 '
b100101 (
1$
b101111010 %
#18950
0$
b101111011 %
#19000
b100111 '
b100110 (
1$
b101111100 %
#19050
0$
b101111101 %
#19100
b101000 '
b100111 (
1$
b101111110 %
#19150
0$
b101111111 %
#19200
b101001 '
b101000 (
1$
b110000000 %
#19250
0$
b110000001 %
#19300
b101010 '
b101001 (
1$
b110000010 %
#19350
0$
b110000011 %
#19400
b101011 '
b101010 (
1$
b110000100 %
#19450
0$
b110000101 %
#19500
b101100 '
b101011 (
1$
b110000110 %
#19550
0$
b110000111 %
#19600
b101101 '
b101100 (
1$
b110001000 %
#19650
0$
b110001001 %
#19700
b101110 '
b101101 (
1$
b110001010 %
#19750
0$
b110001011 %
#19800
b101111 '
b101110 (
1$
b110001100 %
#19850
0$
b110001101 %
#19900
b110000 '
b101111 (
1$
b110001110 %
#19950
0$
b110001111 %
#20000
b110001 '
b110000 (
1$
b110010000 %
#20050
0$
b110010001 %
#20100
1&
b110010 '
b110001 (
1$
b110010010 %
#20150
0$
b110010011 %
#20200
0&
b1 '
b0 (
0!
0)
1$
b110010100 %
#20250
0$
b110010101 %
#20300
b10 '
b1 (
1$
b110010110 %
#20350
0$
b110010111 %
#20400
b11 '
b10 (
1$
b110011000 %
#20450
0$
b110011001 %
#20500
b100 '
b11 (
1$
b110011010 %
#20550
0$
b110011011 %
#20600
b101 '
b100 (
1$
b110011100 %
#20650
0$
b110011101 %
#20700
b110 '
b101 (
1$
b110011110 %
#20750
0$
b110011111 %
#20800
b111 '
b110 (
1$
b110100000 %
#20850
0$
b110100001 %
#20900
b1000 '
b111 (
1$
b110100010 %
#20950
0$
b110100011 %
#21000
b1001 '
b1000 (
1$
b110100100 %
#21050
0$
b110100101 %
#21100
b1010 '
b1001 (
1$
b110100110 %
#21150
0$
b110100111 %
#21200
b1011 '
b1010 (
1$
b110101000 %
#21250
0$
b110101001 %
#21300
b1100 '
b1011 (
1$
b110101010 %
#21350
0$
b110101011 %
#21400
b1101 '
b1100 (
1$
b110101100 %
#21450
0$
b110101101 %
#21500
b1110 '
b1101 (
1$
b110101110 %
#21550
0$
b110101111 %
#21600
b1111 '
b1110 (
1$
b110110000 %
#21650
0$
b110110001 %
#21700
b10000 '
b1111 (
1$
b110110010 %
#21750
0$
b110110011 %
#21800
b10001 '
b10000 (
1$
b110110100 %
#21850
0$
b110110101 %
#21900
b10010 '
b10001 (
1$
b110110110 %
#21950
0$
b110110111 %
#22000
b10011 '
b10010 (
1$
b110111000 %
#22050
0$
b110111001 %
#22100
b10100 '
b10011 (
1$
b110111010 %
#22150
0$
b110111011 %
#22200
b10101 '
b10100 (
1$
b110111100 %
#22250
0$
b110111101 %
#22300
b10110 '
b10101 (
1$
b110111110 %
#22350
0$
b110111111 %
#22400
b10111 '
b10110 (
1$
b111000000 %
#22450
0$
b111000001 %
#22500
b11000 '
b10111 (
1$
b111000010 %
#22550
0$
b111000011 %
#22600
b11001 '
b11000 (
1$
b111000100 %
#22650
0$
b111000101 %
#22700
b11010 '
b11001 (
1$
b111000110 %
#22750
0$
b111000111 %
#22800
b11011 '
b11010 (
1$
b111001000 %
#22850
0$
b111001001 %
#22900
b11100 '
b11011 (
1$
b111001010 %
#22950
0$
b111001011 %
#23000
b11101 '
b11100 (
1$
b111001100 %
#23050
0$
b111001101 %
#23100
b11110 '
b11101 (
1$
b111001110 %
#23150
0$
b111001111 %
#23200
b11111 '
b11110 (
1$
b111010000 %
#23250
0$
b111010001 %
#23300
b100000 '
b11111 (
1$
b111010010 %
#23350
0$
b111010011 %
#23400
b100001 '
b100000 (
1$
b111010100 %
#23450
0$
b111010101 %
#23500
b100010 '
b100001 (
1$
b111010110 %
#23550
0$
b111010111 %
#23600
b100011 '
b100010 (
1$
b111011000 %
#23650
0$
b111011001 %
#23700
b100100 '
b100011 (
1$
b111011010 %
#23750
0$
b111011011 %
#23800
b100101 '
b100100 (
1$
b111011100 %
#23850
0$
b111011101 %
#23900
b100110 '
b100101 (
1$
b111011110 %
#23950
0$
b111011111 %
#24000
b100111 '
b100110 (
1$
b111100000 %
#24050
0$
b111100001 %
#24100
b101000 '
b100111 (
1$
b111100010 %
#24150
0$
b111100011 %
#24200
b101001 '
b101000 (
1$
b111100100 %
#24250
0$
b111100101 %
#24300
b101010 '
b101001 (
1$
b111100110 %
#24350
0$
b111100111 %
#24400
b101011 '
b101010 (
1$
b111101000 %
#24450
0$
b111101001 %
#24500
b101100 '
b101011 (
1$
b111101010 %
#24550
0$
b111101011 %
#24600
b101101 '
b101100 (
1$
b111101100 %
#24650
0$
b111101101 %
#24700
b101110 '
b101101 (
1$
b111101110 %
#24750
0$
b111101111 %
#24800
b101111 '
b101110 (
1$
b111110000 %
#24850
0$
b111110001 %
#24900
b110000 '
b101111 (
1$
b111110010 %
#24950
0$
b111110011 %
#25000
b110001 '
b110000 (
1$
b111110100 %
#25050
0$
b111110101 %
#25100
1&
b110010 '
b110001 (
1$
b111110110 %
#25150
0$
b111110111 %
#25200
0&
b1 '
b0 (
1!
1)
1$
b111111000 %
#25250
0$
b111111001 %
#25300
b10 '
b1 (
1$
b111111010 %
#25350
0$
b111111011 %
#25400
b11 '
b10 (
1$
b111111100 %
#25450
0$
b111111101 %
#25500
b100 '
b11 (
1$
b111111110 %
#25550
0$
b111111111 %
#25600
b101 '
b100 (
1$
b1000000000 %
#25650
0$
b1000000001 %
#25700
b110 '
b101 (
1$
b1000000010 %
#25750
0$
b1000000011 %
#25800
b111 '
b110 (
1$
b1000000100 %
#25850
0$
b1000000101 %
#25900
b1000 '
b111 (
1$
b1000000110 %
#25950
0$
b1000000111 %
#26000
b1001 '
b1000 (
1$
b1000001000 %
#26050
0$
b1000001001 %
#26100
b1010 '
b1001 (
1$
b1000001010 %
#26150
0$
b1000001011 %
#26200
b1011 '
b1010 (
1$
b1000001100 %
#26250
0$
b1000001101 %
#26300
b1100 '
b1011 (
1$
b1000001110 %
#26350
0$
b1000001111 %
#26400
b1101 '
b1100 (
1$
b1000010000 %
#26450
0$
b1000010001 %
#26500
b1110 '
b1101 (
1$
b1000010010 %
#26550
0$
b1000010011 %
#26600
b1111 '
b1110 (
1$
b1000010100 %
#26650
0$
b1000010101 %
#26700
b10000 '
b1111 (
1$
b1000010110 %
#26750
0$
b1000010111 %
#26800
b10001 '
b10000 (
1$
b1000011000 %
#26850
0$
b1000011001 %
#26900
b10010 '
b10001 (
1$
b1000011010 %
#26950
0$
b1000011011 %
#27000
b10011 '
b10010 (
1$
b1000011100 %
#27050
0$
b1000011101 %
#27100
b10100 '
b10011 (
1$
b1000011110 %
#27150
0$
b1000011111 %
#27200
b10101 '
b10100 (
1$
b1000100000 %
#27250
0$
b1000100001 %
#27300
b10110 '
b10101 (
1$
b1000100010 %
#27350
0$
b1000100011 %
#27400
b10111 '
b10110 (
1$
b1000100100 %
#27450
0$
b1000100101 %
#27500
b11000 '
b10111 (
1$
b1000100110 %
#27550
0$
b1000100111 %
#27600
b11001 '
b11000 (
1$
b1000101000 %
#27650
0$
b1000101001 %
#27700
b11010 '
b11001 (
1$
b1000101010 %
#27750
0$
b1000101011 %
#27800
b11011 '
b11010 (
1$
b1000101100 %
#27850
0$
b1000101101 %
#27900
b11100 '
b11011 (
1$
b1000101110 %
#27950
0$
b1000101111 %
#28000
b11101 '
b11100 (
1$
b1000110000 %
#28050
0$
b1000110001 %
#28100
b11110 '
b11101 (
1$
b1000110010 %
#28150
0$
b1000110011 %
#28200
b11111 '
b11110 (
1$
b1000110100 %
#28250
0$
b1000110101 %
#28300
b100000 '
b11111 (
1$
b1000110110 %
#28350
0$
b1000110111 %
#28400
b100001 '
b100000 (
1$
b1000111000 %
#28450
0$
b1000111001 %
#28500
b100010 '
b100001 (
1$
b1000111010 %
#28550
0$
b1000111011 %
#28600
b100011 '
b100010 (
1$
b1000111100 %
#28650
0$
b1000111101 %
#28700
b100100 '
b100011 (
1$
b1000111110 %
#28750
0$
b1000111111 %
#28800
b100101 '
b100100 (
1$
b1001000000 %
#28850
0$
b1001000001 %
#28900
b100110 '
b100101 (
1$
b1001000010 %
#28950
0$
b1001000011 %
#29000
b100111 '
b100110 (
1$
b1001000100 %
#29050
0$
b1001000101 %
#29100
b101000 '
b100111 (
1$
b1001000110 %
#29150
0$
b1001000111 %
#29200
b101001 '
b101000 (
1$
b1001001000 %
#29250
0$
b1001001001 %
#29300
b101010 '
b101001 (
1$
b1001001010 %
#29350
0$
b1001001011 %
#29400
b101011 '
b101010 (
1$
b1001001100 %
#29450
0$
b1001001101 %
#29500
b101100 '
b101011 (
1$
b1001001110 %
#29550
0$
b1001001111 %
#29600
b101101 '
b101100 (
1$
b1001010000 %
#29650
0$
b1001010001 %
#29700
b101110 '
b101101 (
1$
b1001010010 %
#29750
0$
b1001010011 %
#29800
b101111 '
b101110 (
1$
b1001010100 %
#29850
0$
b1001010101 %
#29900
b110000 '
b101111 (
1$
b1001010110 %
#29950
0$
b1001010111 %
#30000
b110001 '
b110000 (
1$
b1001011000 %
#30050
0$
b1001011001 %
#30100
1&
b110010 '
b110001 (
1$
b1001011010 %
#30150
0$
b1001011011 %
#30200
0&
b1 '
b0 (
0!
0)
1$
b1001011100 %
#30250
0$
b1001011101 %
#30300
b10 '
b1 (
1$
b1001011110 %
#30350
0$
b1001011111 %
#30400
b11 '
b10 (
1$
b1001100000 %
#30450
0$
b1001100001 %
#30500
b100 '
b11 (
1$
b1001100010 %
#30550
0$
b1001100011 %
#30600
b101 '
b100 (
1$
b1001100100 %
#30650
0$
b1001100101 %
#30700
b110 '
b101 (
1$
b1001100110 %
#30750
0$
b1001100111 %
#30800
b111 '
b110 (
1$
b1001101000 %
#30850
0$
b1001101001 %
#30900
b1000 '
b111 (
1$
b1001101010 %
#30950
0$
b1001101011 %
#31000
b1001 '
b1000 (
1$
b1001101100 %
#31050
0$
b1001101101 %
#31100
b1010 '
b1001 (
1$
b1001101110 %
#31150
0$
b1001101111 %
#31200
b1011 '
b1010 (
1$
b1001110000 %
#31250
0$
b1001110001 %
#31300
b1100 '
b1011 (
1$
b1001110010 %
#31350
0$
b1001110011 %
#31400
b1101 '
b1100 (
1$
b1001110100 %
#31450
0$
b1001110101 %
#31500
b1110 '
b1101 (
1$
b1001110110 %
#31550
0$
b1001110111 %
#31600
b1111 '
b1110 (
1$
b1001111000 %
#31650
0$
b1001111001 %
#31700
b10000 '
b1111 (
1$
b1001111010 %
#31750
0$
b1001111011 %
#31800
b10001 '
b10000 (
1$
b1001111100 %
#31850
0$
b1001111101 %
#31900
b10010 '
b10001 (
1$
b1001111110 %
#31950
0$
b1001111111 %
#32000
b10011 '
b10010 (
1$
b1010000000 %
#32050
0$
b1010000001 %
#32100
b10100 '
b10011 (
1$
b1010000010 %
#32150
0$
b1010000011 %
#32200
b10101 '
b10100 (
1$
b1010000100 %
#32250
0$
b1010000101 %
#32300
b10110 '
b10101 (
1$
b1010000110 %
#32350
0$
b1010000111 %
#32400
b10111 '
b10110 (
1$
b1010001000 %
#32450
0$
b1010001001 %
#32500
b11000 '
b10111 (
1$
b1010001010 %
#32550
0$
b1010001011 %
#32600
b11001 '
b11000 (
1$
b1010001100 %
#32650
0$
b1010001101 %
#32700
b11010 '
b11001 (
1$
b1010001110 %
#32750
0$
b1010001111 %
#32800
b11011 '
b11010 (
1$
b1010010000 %
#32850
0$
b1010010001 %
#32900
b11100 '
b11011 (
1$
b1010010010 %
#32950
0$
b1010010011 %
#33000
b11101 '
b11100 (
1$
b1010010100 %
#33050
0$
b1010010101 %
#33100
b11110 '
b11101 (
1$
b1010010110 %
#33150
0$
b1010010111 %
#33200
b11111 '
b11110 (
1$
b1010011000 %
#33250
0$
b1010011001 %
#33300
b100000 '
b11111 (
1$
b1010011010 %
#33350
0$
b1010011011 %
#33400
b100001 '
b100000 (
1$
b1010011100 %
#33450
0$
b1010011101 %
#33500
b100010 '
b100001 (
1$
b1010011110 %
#33550
0$
b1010011111 %
#33600
b100011 '
b100010 (
1$
b1010100000 %
#33650
0$
b1010100001 %
#33700
b100100 '
b100011 (
1$
b1010100010 %
#33750
0$
b1010100011 %
#33800
b100101 '
b100100 (
1$
b1010100100 %
#33850
0$
b1010100101 %
#33900
b100110 '
b100101 (
1$
b1010100110 %
#33950
0$
b1010100111 %
#34000
b100111 '
b100110 (
1$
b1010101000 %
#34050
0$
b1010101001 %
#34100
b101000 '
b100111 (
1$
b1010101010 %
